{"version":1,"resource":"file:///home/max/.config/polybar/config.ini","entries":[{"id":"2Adi.ini","timestamp":1745696125388},{"id":"iSzk.ini","timestamp":1745946524192},{"id":"LgKG.ini","timestamp":1745947159988},{"id":"FdgL.ini","timestamp":1745947448012},{"id":"sPuz.ini","timestamp":1745947464757},{"id":"NoG8.ini","timestamp":1745947525111},{"id":"bgSz.ini","timestamp":1745947608276},{"id":"0RzS.ini","timestamp":1745947644363},{"id":"oe1r.ini","timestamp":1745947891375},{"id":"aUCl.ini","timestamp":1745947936843},{"id":"eXxh.ini","timestamp":1745947951544},{"id":"87TF.ini","timestamp":1745947983534},{"id":"IjIc.ini","timestamp":1745948030787},{"id":"dEaV.ini","timestamp":1745948060560}]}